aiohttp_route_middleware/__init__.py
aiohttp_route_middleware/web_urldispatcher.py
aiohttp_route_middleware-0.0.2.dist-info/METADATA
aiohttp_route_middleware-0.0.2.dist-info/RECORD
aiohttp_route_middleware-0.0.2.dist-info/WHEEL
aiohttp_route_middleware-0.0.2.dist-info/top_level.txt
