Metadata-Version: 2.1
Name: aiohttp-route-middleware
Version: 0.0.2
Summary: Local middleware routing for aiohttp.
Home-page: https://github.com/rob-blackbourn/aiohttp-route-middleware/
Author: Rob Blackbourn
Author-email: rob.blackbourn@gmail.com
License: Apache 2
Platform: UNKNOWN
Classifier: License :: OSI Approved :: Apache Software License
Classifier: Intended Audience :: Developers
Classifier: Programming Language :: Python
Classifier: Programming Language :: Python :: 3
Classifier: Programming Language :: Python :: 3.5
Classifier: Programming Language :: Python :: 3.6
Classifier: Topic :: Internet :: WWW/HTTP
Classifier: Framework :: AsyncIO
Requires-Python: ~=3.6
Requires-Dist: aiohttp (>=3.0)
